Workbook

Sheet WACC
A1: COSTO PROMEDIO PONDERADO DE CAPITAL (WACC)
A3: Datos de entrada (amarillo = editable)
A4: Tasa libre de riesgo (Rf) | B4: 0.035
A5: Beta apalancada de la empresa | B5: 1.1
A6: Prima por riesgo de mercado (MRP) | B6: 0.055
A7: Costo de la deuda antes de impuestos (rd) | B7: 0.07
A8: Tasa de impuestos | B8: 0.3
A9: Valor de mercado del patrimonio (E) | B9: 400
A10: Valor de mercado de la deuda (D) | B10: 200
A12: Calculos
A13: Costo del patrimonio re = Rf + beta x MRP (CAPM) | B13: =B4+B5*B6
A14: Costo de la deuda despues de impuestos rd x (1-t) | B14: =B7*(1-B8)
A15: Valor total de la empresa V = E + D | B15: =B9+B10
A16: Peso del patrimonio E/V | B16: =B9/B15
A17: Peso de la deuda D/V | B17: =B10/B15
A19: WACC | B19: =B16*B13+B17*B14
A21: Los pesos deben ir a valor de MERCADO, nunca contable.
A22: Si subes la deuda, el beta del patrimonio deberia subir tambien: el WACC no baja indefinidamente.

Sheet DCF
A1: VALUACION POR DESCUENTO DE FLUJOS (DCF)
A3: Supuestos
A4: Origen del WACC (1 = hoja WACC 2 = manual) | B4: 2
A5: WACC calculado en la hoja WACC | B5: =WACC!B19
A6: WACC manual | B6: 0.12
A7: WACC EN USO | B7: =IFERROR(CHOOSE(B4,B5,B6),"Origen debe ser 1 o 2")
A8: Crecimiento perpetuo g | B8: 0.015
A9: Deuda neta | B9: 40
A10: Acciones en circulacion (millones) | B10: 5
A12: Flujos explicitos
A13: Concepto | B13: Ano 1 | C13: Ano 2 | D13: Ano 3
A14: FCFF proyectado | B14: 50 | C14: 60 | D14: 70
A15: Factor de descuento 1/(1+WACC)^t | B15: =1/(1+$B7)^1 | C15: =1/(1+$B7)^2 | D15: =1/(1+$B7)^3
A16: Valor presente del FCFF | B16: =B14*B15 | C16: =C14*C15 | D16: =D14*D15
A17: Suma de VP explicitos | B17: =SUM(B16:D16)
A19: Valor terminal (Gordon)
A20: FCFF del ano 4 = FCFF3 x (1+g) | B20: =D14*(1+$B8)
A21: Valor terminal al final del ano 3 | B21: =IFERROR(B20/($B7-$B8),"g debe ser menor que el WACC")
A22: VP del valor terminal (descontado 3 anos, NO 4) | B22: =B21*D15
A23: Error clasico: descontar el VT un periodo de mas. Gordon lo situa en el ano n, no en n+1.
A25: Puente de valuacion
A26: Enterprise Value | B26: =B17+B22
A27: (-) Deuda neta | B27: =-B9
A28: Equity Value | B28: =B26-B9
A29: VALOR INTRINSECO POR ACCION | B29: =IFERROR(B28/B10,"Revisa el numero de acciones")
A31: Peso del valor terminal sobre el EV | B31: =B22/B26
A32: Si el VT supera el 80% del EV, el modelo depende mas de un supuesto que del analisis.

Sheet Sensibilidad
A1: SENSIBILIDAD DEL PRECIO POR ACCION: WACC x crecimiento perpetuo (g)
A3: Cada celda recalcula el DCF completo con ese par (WACC, g). Un DCF serio se presenta como rango, no como un numero.
A5: WACC \ g | B5: 0.005 | C5: 0.01 | D5: 0.015 | E5: 0.02 | F5: 0.025 | G5: 0.03
A6: 0.1 | B6: =IFERROR((DCF!B14/(1+$A6)^1+DCF!C14/(1+$A6)^2+DCF!D14/(1+$A6)^3+(DCF!D14*(1+B$5)/($A6-B$5))/(1+$A6)^3-DCF!$B9)/DCF!$B10,"n/a") | C6: =IFERROR((DCF!B14/(1+$A6)^1+DCF!C14/(1+$A6)^2+DCF!D14/(1+$A6)^3+(DCF!D14*(1+C$5)/($A6-C$5))/(1+$A6)^3-DCF!$B9)/DCF!$B10,"n/a") | D6: =IFERROR((DCF!B14/(1+$A6)^1+DCF!C14/(1+$A6)^2+DCF!D14/(1+$A6)^3+(DCF!D14*(1+D$5)/($A6-D$5))/(1+$A6)^3-DCF!$B9)/DCF!$B10,"n/a") | E6: =IFERROR((DCF!B14/(1+$A6)^1+DCF!C14/(1+$A6)^2+DCF!D14/(1+$A6)^3+(DCF!D14*(1+E$5)/($A6-E$5))/(1+$A6)^3-DCF!$B9)/DCF!$B10,"n/a") | F6: =IFERROR((DCF!B14/(1+$A6)^1+DCF!C14/(1+$A6)^2+DCF!D14/(1+$A6)^3+(DCF!D14*(1+F$5)/($A6-F$5))/(1+$A6)^3-DCF!$B9)/DCF!$B10,"n/a") | G6: =IFERROR((DCF!B14/(1+$A6)^1+DCF!C14/(1+$A6)^2+DCF!D14/(1+$A6)^3+(DCF!D14*(1+G$5)/($A6-G$5))/(1+$A6)^3-DCF!$B9)/DCF!$B10,"n/a")
A7: 0.11 | B7: =IFERROR((DCF!B14/(1+$A7)^1+DCF!C14/(1+$A7)^2+DCF!D14/(1+$A7)^3+(DCF!D14*(1+B$5)/($A7-B$5))/(1+$A7)^3-DCF!$B9)/DCF!$B10,"n/a") | C7: =IFERROR((DCF!B14/(1+$A7)^1+DCF!C14/(1+$A7)^2+DCF!D14/(1+$A7)^3+(DCF!D14*(1+C$5)/($A7-C$5))/(1+$A7)^3-DCF!$B9)/DCF!$B10,"n/a") | D7: =IFERROR((DCF!B14/(1+$A7)^1+DCF!C14/(1+$A7)^2+DCF!D14/(1+$A7)^3+(DCF!D14*(1+D$5)/($A7-D$5))/(1+$A7)^3-DCF!$B9)/DCF!$B10,"n/a") | E7: =IFERROR((DCF!B14/(1+$A7)^1+DCF!C14/(1+$A7)^2+DCF!D14/(1+$A7)^3+(DCF!D14*(1+E$5)/($A7-E$5))/(1+$A7)^3-DCF!$B9)/DCF!$B10,"n/a") | F7: =IFERROR((DCF!B14/(1+$A7)^1+DCF!C14/(1+$A7)^2+DCF!D14/(1+$A7)^3+(DCF!D14*(1+F$5)/($A7-F$5))/(1+$A7)^3-DCF!$B9)/DCF!$B10,"n/a") | G7: =IFERROR((DCF!B14/(1+$A7)^1+DCF!C14/(1+$A7)^2+DCF!D14/(1+$A7)^3+(DCF!D14*(1+G$5)/($A7-G$5))/(1+$A7)^3-DCF!$B9)/DCF!$B10,"n/a")
A8: 0.12 | B8: =IFERROR((DCF!B14/(1+$A8)^1+DCF!C14/(1+$A8)^2+DCF!D14/(1+$A8)^3+(DCF!D14*(1+B$5)/($A8-B$5))/(1+$A8)^3-DCF!$B9)/DCF!$B10,"n/a") | C8: =IFERROR((DCF!B14/(1+$A8)^1+DCF!C14/(1+$A8)^2+DCF!D14/(1+$A8)^3+(DCF!D14*(1+C$5)/($A8-C$5))/(1+$A8)^3-DCF!$B9)/DCF!$B10,"n/a") | D8: =IFERROR((DCF!B14/(1+$A8)^1+DCF!C14/(1+$A8)^2+DCF!D14/(1+$A8)^3+(DCF!D14*(1+D$5)/($A8-D$5))/(1+$A8)^3-DCF!$B9)/DCF!$B10,"n/a") | E8: =IFERROR((DCF!B14/(1+$A8)^1+DCF!C14/(1+$A8)^2+DCF!D14/(1+$A8)^3+(DCF!D14*(1+E$5)/($A8-E$5))/(1+$A8)^3-DCF!$B9)/DCF!$B10,"n/a") | F8: =IFERROR((DCF!B14/(1+$A8)^1+DCF!C14/(1+$A8)^2+DCF!D14/(1+$A8)^3+(DCF!D14*(1+F$5)/($A8-F$5))/(1+$A8)^3-DCF!$B9)/DCF!$B10,"n/a") | G8: =IFERROR((DCF!B14/(1+$A8)^1+DCF!C14/(1+$A8)^2+DCF!D14/(1+$A8)^3+(DCF!D14*(1+G$5)/($A8-G$5))/(1+$A8)^3-DCF!$B9)/DCF!$B10,"n/a")
A9: 0.13 | B9: =IFERROR((DCF!B14/(1+$A9)^1+DCF!C14/(1+$A9)^2+DCF!D14/(1+$A9)^3+(DCF!D14*(1+B$5)/($A9-B$5))/(1+$A9)^3-DCF!$B9)/DCF!$B10,"n/a") | C9: =IFERROR((DCF!B14/(1+$A9)^1+DCF!C14/(1+$A9)^2+DCF!D14/(1+$A9)^3+(DCF!D14*(1+C$5)/($A9-C$5))/(1+$A9)^3-DCF!$B9)/DCF!$B10,"n/a") | D9: =IFERROR((DCF!B14/(1+$A9)^1+DCF!C14/(1+$A9)^2+DCF!D14/(1+$A9)^3+(DCF!D14*(1+D$5)/($A9-D$5))/(1+$A9)^3-DCF!$B9)/DCF!$B10,"n/a") | E9: =IFERROR((DCF!B14/(1+$A9)^1+DCF!C14/(1+$A9)^2+DCF!D14/(1+$A9)^3+(DCF!D14*(1+E$5)/($A9-E$5))/(1+$A9)^3-DCF!$B9)/DCF!$B10,"n/a") | F9: =IFERROR((DCF!B14/(1+$A9)^1+DCF!C14/(1+$A9)^2+DCF!D14/(1+$A9)^3+(DCF!D14*(1+F$5)/($A9-F$5))/(1+$A9)^3-DCF!$B9)/DCF!$B10,"n/a") | G9: =IFERROR((DCF!B14/(1+$A9)^1+DCF!C14/(1+$A9)^2+DCF!D14/(1+$A9)^3+(DCF!D14*(1+G$5)/($A9-G$5))/(1+$A9)^3-DCF!$B9)/DCF!$B10,"n/a")
A10: 0.14 | B10: =IFERROR((DCF!B14/(1+$A10)^1+DCF!C14/(1+$A10)^2+DCF!D14/(1+$A10)^3+(DCF!D14*(1+B$5)/($A10-B$5))/(1+$A10)^3-DCF!$B9)/DCF!$B10,"n/a") | C10: =IFERROR((DCF!B14/(1+$A10)^1+DCF!C14/(1+$A10)^2+DCF!D14/(1+$A10)^3+(DCF!D14*(1+C$5)/($A10-C$5))/(1+$A10)^3-DCF!$B9)/DCF!$B10,"n/a") | D10: =IFERROR((DCF!B14/(1+$A10)^1+DCF!C14/(1+$A10)^2+DCF!D14/(1+$A10)^3+(DCF!D14*(1+D$5)/($A10-D$5))/(1+$A10)^3-DCF!$B9)/DCF!$B10,"n/a") | E10: =IFERROR((DCF!B14/(1+$A10)^1+DCF!C14/(1+$A10)^2+DCF!D14/(1+$A10)^3+(DCF!D14*(1+E$5)/($A10-E$5))/(1+$A10)^3-DCF!$B9)/DCF!$B10,"n/a") | F10: =IFERROR((DCF!B14/(1+$A10)^1+DCF!C14/(1+$A10)^2+DCF!D14/(1+$A10)^3+(DCF!D14*(1+F$5)/($A10-F$5))/(1+$A10)^3-DCF!$B9)/DCF!$B10,"n/a") | G10: =IFERROR((DCF!B14/(1+$A10)^1+DCF!C14/(1+$A10)^2+DCF!D14/(1+$A10)^3+(DCF!D14*(1+G$5)/($A10-G$5))/(1+$A10)^3-DCF!$B9)/DCF!$B10,"n/a")
A11: 0.15 | B11: =IFERROR((DCF!B14/(1+$A11)^1+DCF!C14/(1+$A11)^2+DCF!D14/(1+$A11)^3+(DCF!D14*(1+B$5)/($A11-B$5))/(1+$A11)^3-DCF!$B9)/DCF!$B10,"n/a") | C11: =IFERROR((DCF!B14/(1+$A11)^1+DCF!C14/(1+$A11)^2+DCF!D14/(1+$A11)^3+(DCF!D14*(1+C$5)/($A11-C$5))/(1+$A11)^3-DCF!$B9)/DCF!$B10,"n/a") | D11: =IFERROR((DCF!B14/(1+$A11)^1+DCF!C14/(1+$A11)^2+DCF!D14/(1+$A11)^3+(DCF!D14*(1+D$5)/($A11-D$5))/(1+$A11)^3-DCF!$B9)/DCF!$B10,"n/a") | E11: =IFERROR((DCF!B14/(1+$A11)^1+DCF!C14/(1+$A11)^2+DCF!D14/(1+$A11)^3+(DCF!D14*(1+E$5)/($A11-E$5))/(1+$A11)^3-DCF!$B9)/DCF!$B10,"n/a") | F11: =IFERROR((DCF!B14/(1+$A11)^1+DCF!C14/(1+$A11)^2+DCF!D14/(1+$A11)^3+(DCF!D14*(1+F$5)/($A11-F$5))/(1+$A11)^3-DCF!$B9)/DCF!$B10,"n/a") | G11: =IFERROR((DCF!B14/(1+$A11)^1+DCF!C14/(1+$A11)^2+DCF!D14/(1+$A11)^3+(DCF!D14*(1+G$5)/($A11-G$5))/(1+$A11)^3-DCF!$B9)/DCF!$B10,"n/a")
