Workbook

Sheet Supuestos
A1: SUPUESTOS DEL MODELO · celdas amarillas = editables
A3: Selector de escenario
A4: Escenario activo (1=Base 2=Optimista 3=Pesimista) | B4: 1
A5: Cambia solo este numero: todo el modelo se recalcula.
A7: Tabla de escenarios
A8: Supuesto | B8: Base | C8: Optimista | D8: Pesimista
A9: Crecimiento de ventas | B9: 0.1 | C9: 0.18 | D9: 0.02
A10: Margen EBITDA | B10: 0.2 | C10: 0.24 | D10: 0.15
A11: Tasa de impuestos | B11: 0.25 | C11: 0.25 | D11: 0.25
A12: Tasa de interes de la deuda | B12: 0.05 | C12: 0.045 | D12: 0.07
A14: Supuestos activos (calculados con CHOOSE / ELEGIR)
A15: Crecimiento de ventas | B15: =IFERROR(CHOOSE($B4,B9,C9,D9),"Revisa el escenario")
A16: Margen EBITDA | B16: =IFERROR(CHOOSE($B4,B10,C10,D10),"Revisa el escenario")
A17: Tasa de impuestos | B17: =IFERROR(CHOOSE($B4,B11,C11,D11),"Revisa el escenario")
A18: Tasa de interes de la deuda | B18: =IFERROR(CHOOSE($B4,B12,C12,D12),"Revisa el escenario")
A20: Supuestos fijos
A21: Depreciacion anual | B21: 20
A22: CapEx anual | B22: 50
A23: Ventas del Ano 0 | B23: 1000
A25: Balance inicial (Ano 0)
A26: Efectivo | B26: 100
A27: Inventario | B27: 200
A28: PP&E neto | B28: 800
A29: Cuentas por pagar | B29: 100
A30: Deuda a largo plazo | B30: 600
A31: Ganancias retenidas | B31: 400

Sheet P&L
A1: ESTADO DE RESULTADOS PROYECTADO
A3: Concepto | B3: Ano 0 | C3: Ano 1 | D3: Ano 2 | E3: Ano 3 | F3: Ano 4 | G3: Ano 5
A4: Ventas | B4: =Supuestos!$B$23 | C4: =B4*(1+Supuestos!$B$15) | D4: =C4*(1+Supuestos!$B$15) | E4: =D4*(1+Supuestos!$B$15) | F4: =E4*(1+Supuestos!$B$15) | G4: =F4*(1+Supuestos!$B$15)
A5: EBITDA | B5: =B4*Supuestos!$B$16 | C5: =C4*Supuestos!$B$16 | D5: =D4*Supuestos!$B$16 | E5: =E4*Supuestos!$B$16 | F5: =F4*Supuestos!$B$16 | G5: =G4*Supuestos!$B$16
A6: (-) Depreciacion | B6: =-Supuestos!$B$21 | C6: =-Supuestos!$B$21 | D6: =-Supuestos!$B$21 | E6: =-Supuestos!$B$21 | F6: =-Supuestos!$B$21 | G6: =-Supuestos!$B$21
A7: EBIT | B7: =B5+B6 | C7: =C5+C6 | D7: =D5+D6 | E7: =E5+E6 | F7: =F5+F6 | G7: =G5+G6
A8: (-) Gasto financiero | B8: =-Supuestos!$B$30*Supuestos!$B$18 | C8: =-Supuestos!$B$30*Supuestos!$B$18 | D8: =-Supuestos!$B$30*Supuestos!$B$18 | E8: =-Supuestos!$B$30*Supuestos!$B$18 | F8: =-Supuestos!$B$30*Supuestos!$B$18 | G8: =-Supuestos!$B$30*Supuestos!$B$18
A9: EBT (utilidad antes de impuestos) | B9: =B7+B8 | C9: =C7+C8 | D9: =D7+D8 | E9: =E7+E8 | F9: =F7+F8 | G9: =G7+G8
A10: (-) Impuestos | B10: =-MAX(0,B9)*Supuestos!$B$17 | C10: =-MAX(0,C9)*Supuestos!$B$17 | D10: =-MAX(0,D9)*Supuestos!$B$17 | E10: =-MAX(0,E9)*Supuestos!$B$17 | F10: =-MAX(0,F9)*Supuestos!$B$17 | G10: =-MAX(0,G9)*Supuestos!$B$17
A11: UTILIDAD NETA | B11: =B9+B10 | C11: =C9+C10 | D11: =D9+D10 | E11: =E9+E10 | F11: =F9+F10 | G11: =G9+G10
A13: Margenes de control
A14: Margen EBITDA | B14: =IFERROR(B5/B4,0) | C14: =IFERROR(C5/C4,0) | D14: =IFERROR(D5/D4,0) | E14: =IFERROR(E5/E4,0) | F14: =IFERROR(F5/F4,0) | G14: =IFERROR(G5/G4,0)
A15: Margen neto | B15: =IFERROR(B11/B4,0) | C15: =IFERROR(C11/C4,0) | D15: =IFERROR(D11/D4,0) | E15: =IFERROR(E11/E4,0) | F15: =IFERROR(F11/F4,0) | G15: =IFERROR(G11/G4,0)
A17: Los impuestos usan MAX(0;EBT): si hay perdida no se paga impuesto (no se modela el credito fiscal).

Sheet Flujo de Efectivo
A1: FLUJO DE EFECTIVO (metodo indirecto)
A3: Concepto | B3: Ano 0 | C3: Ano 1 | D3: Ano 2 | E3: Ano 3 | F3: Ano 4 | G3: Ano 5
A4: Utilidad neta | C4: ='P&L'!C11 | D4: ='P&L'!D11 | E4: ='P&L'!E11 | F4: ='P&L'!F11 | G4: ='P&L'!G11
A5: (+) Depreciacion (no consume caja) | C5: =Supuestos!$B$21 | D5: =Supuestos!$B$21 | E5: =Supuestos!$B$21 | F5: =Supuestos!$B$21 | G5: =Supuestos!$B$21
A6: Flujo de operacion (CFO) | C6: =C4+C5 | D6: =D4+D5 | E6: =E4+E5 | F6: =F4+F5 | G6: =G4+G5
A7: (-) CapEx | C7: =-Supuestos!$B$22 | D7: =-Supuestos!$B$22 | E7: =-Supuestos!$B$22 | F7: =-Supuestos!$B$22 | G7: =-Supuestos!$B$22
A8: Flujo de inversion (CFI) | C8: =C7 | D8: =D7 | E8: =E7 | F8: =F7 | G8: =G7
A9: Flujo de financiamiento (CFF) | C9: 0 | D9: 0 | E9: 0 | F9: 0 | G9: 0
A10: Sin cambios en deuda ni dividendos por simplicidad: modelalos aqui cuando los necesites.
A11: VARIACION NETA DE EFECTIVO | C11: =C6+C8+C9 | D11: =D6+D8+D9 | E11: =E6+E8+E9 | F11: =F6+F8+F9 | G11: =G6+G8+G9
A12: Efectivo inicial | C12: =Supuestos!$B$26 | D12: =C13 | E12: =D13 | F12: =E13 | G12: =F13
A13: EFECTIVO FINAL (el "plug" del balance) | C13: =C12+C11 | D13: =D12+D11 | E13: =E12+E11 | F13: =F12+F11 | G13: =G12+G11
A15: Flujo de caja libre
A16: FCF = CFO - CapEx | C16: =C6+C7 | D16: =D6+D7 | E16: =E6+E7 | F16: =F6+F7 | G16: =G6+G7

Sheet Balance
A1: BALANCE GENERAL PROYECTADO
A3: Concepto | B3: Ano 0 | C3: Ano 1 | D3: Ano 2 | E3: Ano 3 | F3: Ano 4 | G3: Ano 5
A4: ACTIVO
A5: Efectivo | B5: =Supuestos!$B$26 | C5: ='Flujo de Efectivo'!C13 | D5: ='Flujo de Efectivo'!D13 | E5: ='Flujo de Efectivo'!E13 | F5: ='Flujo de Efectivo'!F13 | G5: ='Flujo de Efectivo'!G13
A6: Inventario | B6: =Supuestos!$B$27 | C6: =Supuestos!$B$27 | D6: =Supuestos!$B$27 | E6: =Supuestos!$B$27 | F6: =Supuestos!$B$27 | G6: =Supuestos!$B$27
A7: PP&E neto | B7: =Supuestos!$B$28 | C7: =B7+Supuestos!$B$22-Supuestos!$B$21 | D7: =C7+Supuestos!$B$22-Supuestos!$B$21 | E7: =D7+Supuestos!$B$22-Supuestos!$B$21 | F7: =E7+Supuestos!$B$22-Supuestos!$B$21 | G7: =F7+Supuestos!$B$22-Supuestos!$B$21
A8: TOTAL ACTIVO | B8: =SUM(B5:B7) | C8: =SUM(C5:C7) | D8: =SUM(D5:D7) | E8: =SUM(E5:E7) | F8: =SUM(F5:F7) | G8: =SUM(G5:G7)
A10: PASIVO Y PATRIMONIO
A11: Cuentas por pagar | B11: =Supuestos!$B$29 | C11: =Supuestos!$B$29 | D11: =Supuestos!$B$29 | E11: =Supuestos!$B$29 | F11: =Supuestos!$B$29 | G11: =Supuestos!$B$29
A12: Deuda a largo plazo | B12: =Supuestos!$B$30 | C12: =Supuestos!$B$30 | D12: =Supuestos!$B$30 | E12: =Supuestos!$B$30 | F12: =Supuestos!$B$30 | G12: =Supuestos!$B$30
A13: Ganancias retenidas | B13: =Supuestos!$B$31 | C13: =B13+'P&L'!C11 | D13: =C13+'P&L'!D11 | E13: =D13+'P&L'!E11 | F13: =E13+'P&L'!F11 | G13: =F13+'P&L'!G11
A14: TOTAL PASIVO + PATRIMONIO | B14: =SUM(B11:B13) | C14: =SUM(C11:C13) | D14: =SUM(D11:D13) | E14: =SUM(E11:E13) | F14: =SUM(F11:F13) | G14: =SUM(G11:G13)
A16: COMPROBACION
A17: Activo - (Pasivo + Patrimonio) -> debe ser 0 | B17: =B8-B14 | C17: =C8-C14 | D17: =D8-D14 | E17: =E8-E14 | F17: =F8-F14 | G17: =G8-G14
A19: Verde = el balance cuadra. Rojo = hay un error de logica: NUNCA lo fuerces a mano.
