Workbook

Sheet 1 Supuestos
A1: SUPUESTOS · sustituye los datos de ejemplo por los de tu empresa
A3: Regla de oro: ningun numero escrito a mano fuera de esta hoja. Todo lo demas son formulas.
A5: Escenario
A6: Escenario (1=Base 2=Optimista 3=Pesimista) | B6: 1
A8: Supuesto | B8: Base | C8: Optimista | D8: Pesimista
A9: Crecimiento de ventas | B9: 0.08 | C9: 0.14 | D9: 0.02
A10: Margen EBIT | B10: 0.18 | C10: 0.22 | D10: 0.13
A11: CapEx como % de ventas | B11: 0.06 | C11: 0.05 | D11: 0.08
A12: Cambio en capital de trabajo como % de ventas | B12: 0.02 | C12: 0.015 | D12: 0.035
A14: Supuestos activos
A15: Crecimiento de ventas | B15: =IFERROR(CHOOSE($B6,B9,C9,D9),"Escenario invalido")
A16: Margen EBIT | B16: =IFERROR(CHOOSE($B6,B10,C10,D10),"Escenario invalido")
A17: CapEx como % de ventas | B17: =IFERROR(CHOOSE($B6,B11,C11,D11),"Escenario invalido")
A18: Cambio en capital de trabajo como % de ventas | B18: =IFERROR(CHOOSE($B6,B12,C12,D12),"Escenario invalido")
A20: Datos historicos y financieros
A21: Ventas del ultimo ano reportado | B21: 10000
A22: Depreciacion como % de ventas | B22: 0.04
A23: Tasa impositiva efectiva | B23: 0.25
A24: Deuda financiera total | B24: 3000
A25: Efectivo y equivalentes | B25: 800
A26: Acciones en circulacion (millones) | B26: 315
A27: Precio actual de mercado por accion | B27: 42
A29: Costo de capital (WACC)
A30: Tasa libre de riesgo | B30: 0.04
A31: Beta | B31: 1.15
A32: Prima por riesgo de mercado | B32: 0.055
A33: Costo de la deuda antes de impuestos | B33: 0.065
A34: Costo del patrimonio (CAPM) | B34: =B30+B31*B32
A35: Valor de mercado del patrimonio (precio x acciones) | B35: ='1 Supuestos'!$B$27*'1 Supuestos'!$B$26
A36: WACC | B36: =(B35/(B35+'1 Supuestos'!$B$24))*B34+('1 Supuestos'!$B$24/(B35+'1 Supuestos'!$B$24))*B33*(1-'1 Supuestos'!$B$23)
A37: Crecimiento perpetuo (g) | B37: 0.02
A38: g nunca debe superar el crecimiento nominal de la economia (2-3%). Y jamas al WACC.

Sheet 2 Proyeccion
A1: PROYECCION DE FLUJOS A 5 ANOS
A3: Concepto | B3: Ano 0 | C3: Ano 1 | D3: Ano 2 | E3: Ano 3 | F3: Ano 4 | G3: Ano 5
A4: Ventas | B4: ='1 Supuestos'!$B$21 | C4: =B4*(1+'1 Supuestos'!$B$15) | D4: =C4*(1+'1 Supuestos'!$B$15) | E4: =D4*(1+'1 Supuestos'!$B$15) | F4: =E4*(1+'1 Supuestos'!$B$15) | G4: =F4*(1+'1 Supuestos'!$B$15)
A5: EBIT | B5: =B4*'1 Supuestos'!$B$16 | C5: =C4*'1 Supuestos'!$B$16 | D5: =D4*'1 Supuestos'!$B$16 | E5: =E4*'1 Supuestos'!$B$16 | F5: =F4*'1 Supuestos'!$B$16 | G5: =G4*'1 Supuestos'!$B$16
A6: NOPAT = EBIT x (1 - t) | B6: =B5*(1-'1 Supuestos'!$B$23) | C6: =C5*(1-'1 Supuestos'!$B$23) | D6: =D5*(1-'1 Supuestos'!$B$23) | E6: =E5*(1-'1 Supuestos'!$B$23) | F6: =F5*(1-'1 Supuestos'!$B$23) | G6: =G5*(1-'1 Supuestos'!$B$23)
A7: (+) Depreciacion y amortizacion | B7: =B4*'1 Supuestos'!$B$22 | C7: =C4*'1 Supuestos'!$B$22 | D7: =D4*'1 Supuestos'!$B$22 | E7: =E4*'1 Supuestos'!$B$22 | F7: =F4*'1 Supuestos'!$B$22 | G7: =G4*'1 Supuestos'!$B$22
A8: (-) CapEx | B8: =-B4*'1 Supuestos'!$B$17 | C8: =-C4*'1 Supuestos'!$B$17 | D8: =-D4*'1 Supuestos'!$B$17 | E8: =-E4*'1 Supuestos'!$B$17 | F8: =-F4*'1 Supuestos'!$B$17 | G8: =-G4*'1 Supuestos'!$B$17
A9: (-) Cambio en capital de trabajo | B9: =-B4*'1 Supuestos'!$B$18 | C9: =-C4*'1 Supuestos'!$B$18 | D9: =-D4*'1 Supuestos'!$B$18 | E9: =-E4*'1 Supuestos'!$B$18 | F9: =-F4*'1 Supuestos'!$B$18 | G9: =-G4*'1 Supuestos'!$B$18
A10: FCFF | B10: =B6+B7+B8+B9 | C10: =C6+C7+C8+C9 | D10: =D6+D7+D8+D9 | E10: =E6+E7+E8+E9 | F10: =F6+F7+F8+F9 | G10: =G6+G7+G8+G9
A12: El FCFF no resta intereses: pertenece a accionistas Y acreedores, y el financiamiento ya esta en el WACC.

Sheet 3 Valuacion DCF
A1: VALUACION POR DCF
A3: Concepto | B3: Ano 1 | C3: Ano 2 | D3: Ano 3 | E3: Ano 4 | F3: Ano 5
A4: FCFF proyectado | B4: ='2 Proyeccion'!C10 | C4: ='2 Proyeccion'!D10 | D4: ='2 Proyeccion'!E10 | E4: ='2 Proyeccion'!F10 | F4: ='2 Proyeccion'!G10
A5: Factor de descuento | B5: =1/(1+'1 Supuestos'!$B$36)^1 | C5: =1/(1+'1 Supuestos'!$B$36)^2 | D5: =1/(1+'1 Supuestos'!$B$36)^3 | E5: =1/(1+'1 Supuestos'!$B$36)^4 | F5: =1/(1+'1 Supuestos'!$B$36)^5
A6: Valor presente | B6: =B4*B5 | C6: =C4*C5 | D6: =D4*D5 | E6: =E4*E5 | F6: =F4*F5
A8: Suma de VP explicitos | B8: =SUM(B6:F6)
A9: Valor terminal (Gordon) al final del Ano 5 | B9: =IFERROR(F4*(1+'1 Supuestos'!$B$37)/('1 Supuestos'!$B$36-'1 Supuestos'!$B$37),"g >= WACC: revisa los supuestos")
A10: VP del valor terminal | B10: =B9*F5
A11: Peso del valor terminal sobre el EV | B11: =B10/(B8+B10)
A13: Puente al valor por accion
A14: ENTERPRISE VALUE | B14: =B8+B10
A15: (-) Deuda financiera | B15: =-'1 Supuestos'!$B$24
A16: (+) Efectivo y equivalentes | B16: ='1 Supuestos'!$B$25
A17: EQUITY VALUE | B17: =B14-'1 Supuestos'!$B$24+'1 Supuestos'!$B$25
A18: TARGET PRICE POR DCF | B18: =IFERROR(B17/'1 Supuestos'!$B$26,"Revisa las acciones")

Sheet 4 Comparables
A1: VALUACION RELATIVA POR MULTIPLOS (COMPS)
A3: Empresa comparable | B3: EV/EBITDA | C3: P/E | D3: P/S | E3: Crecimiento
A4: Comparable 1 | B4: 6.8 | C4: 14.2 | D4: 1.1 | E4: 0.07
A5: Comparable 2 | B5: 7.6 | C5: 16.4 | D5: 1.4 | E5: 0.11
A6: Comparable 3 | B6: 6.2 | C6: 12.9 | D6: 0.9 | E6: 0.04
A7: Comparable 4 | B7: 7.9 | C7: 17.1 | D7: 1.5 | E7: 0.09
A8: MEDIANA del sector | B8: =MEDIAN(B4:B7) | C8: =MEDIAN(C4:C7) | D8: =MEDIAN(D4:D7) | E8: =MEDIAN(E4:E7)
A9: Usa la MEDIANA, no la media: un solo comparable atipico distorsiona el promedio.
A11: Aplicacion del multiplo a tu empresa
A12: EBITDA del Ano 1 (EBIT + D&A) | B12: ='2 Proyeccion'!C5+'2 Proyeccion'!C7
A13: Enterprise Value implicito (mediana EV/EBITDA x EBITDA) | B13: =B8*B12
A14: Equity Value implicito | B14: =B13-'1 Supuestos'!$B$24+'1 Supuestos'!$B$25
A15: TARGET PRICE POR COMPS | B15: =IFERROR(B14/'1 Supuestos'!$B$26,"Revisa las acciones")
A17: Precio objetivo mezclado (Blended)
A18: Peso del DCF | B18: 0.6
A19: Peso de los Comps | B19: =1-B18
A20: Target price DCF | B20: ='3 Valuacion DCF'!$B$18
A21: Target price Comps | B21: ='4 Comparables'!$B$15
A22: PRECIO OBJETIVO FINAL | B22: =B18*'3 Valuacion DCF'!$B$18+B19*'4 Comparables'!$B$15
A23: Precio actual de mercado | B23: ='1 Supuestos'!$B$27
A24: UPSIDE / DOWNSIDE | B24: =IFERROR(B22/'1 Supuestos'!$B$27-1,"")
A25: RECOMENDACION | B25: =IF(B24>0.15,"COMPRAR",IF(B24<-0.10,"VENDER","MANTENER"))
A26: Los umbrales (+15% / -10%) son convencion habitual de research; ajustalos y justificalos.

Sheet 5 Rubrica
A1: AUTOEVALUACION CONTRA LA RUBRICA (100 puntos)
A3: Puntuate antes de entregar. Escribe tu puntaje en la columna amarilla.
A5: Criterio | B5: Maximo | C5: Tu puntaje
A6: Correctitud matematica: DCF y WACC bien calculados, FCFF pasa la prueba, Excel sin loops rotos | B6: 30 | C6: 0
A7: Profundidad de analisis: explica el POR QUE de los numeros, identifica banderas rojas o ventajas reales | B7: 30 | C7: 0
A8: Coherencia macroeconomica: los supuestos son consistentes con el ciclo y las tasas actuales | B8: 15 | C8: 0
A9: Presentacion y comunicacion: reporte claro, profesional, recomendacion coherente con los numeros | B9: 15 | C9: 0
A10: Gestion de riesgos: riesgos logicos identificados, con coberturas o puntos de salida | B10: 10 | C10: 0
A11: TOTAL | B11: =SUM(B6:B10) | C11: =SUM(C6:C10)
A13: Comprobaciones tecnicas antes de entregar
A14: ☐ El balance del modelo cuadra en TODOS los anos proyectados
A15: ☐ El valor terminal no supera el 85% del Enterprise Value
A16: ☐ g es menor que el WACC y no supera el 3%
A17: ☐ Los tres escenarios (base, optimista, pesimista) funcionan sin errores
A18: ☐ Ninguna celda de calculo tiene numeros escritos a mano
A19: ☐ Las fuentes de los datos historicos estan citadas
